{
  "openapi": "3.0.1",
  "info": {
    "title": "Prova.Api",
    "version": "1.0"
  },
  "paths": {
    "/api/Cliente": {
      "get": {
        "tags": [
          "Cliente"
        ],
        "responses": {
          "200": {
            "description": "OK",
            "content": {
              "text/plain": {
                "schema": {
                  "type": "array",
                  "items": {
                    "$ref": "#/components/schemas/Cliente"
                  }
                }
              },
              "application/json": {
                "schema": {
                  "type": "array",
                  "items": {
                    "$ref": "#/components/schemas/Cliente"
                  }
                }
              },
              "text/json": {
                "schema": {
                  "type": "array",
                  "items": {
                    "$ref": "#/components/schemas/Cliente"
                  }
                }
              }
            }
          }
        }
      },
      "post": {
        "tags": [
          "Cliente"
        ],
        "requestBody": {
          "content": {
            "application/json": {
              "schema": {
                "$ref": "#/components/schemas/Cliente"
              }
            },
            "text/json": {
              "schema": {
                "$ref": "#/components/schemas/Cliente"
              }
            },
            "application/*+json": {
              "schema": {
                "$ref": "#/components/schemas/Cliente"
              }
            }
          }
        },
        "responses": {
          "200": {
            "description": "OK",
            "content": {
              "text/plain": {
                "schema": {
                  "$ref": "#/components/schemas/Cliente"
                }
              },
              "application/json": {
                "schema": {
                  "$ref": "#/components/schemas/Cliente"
                }
              },
              "text/json": {
                "schema": {
                  "$ref": "#/components/schemas/Cliente"
                }
              }
            }
          }
        }
      }
    },
    "/api/Cliente/{id}": {
      "get": {
        "tags": [
          "Cliente"
        ],
        "parameters": [
          {
            "name": "id",
            "in": "path",
            "required": true,
            "schema": {
              "type": "integer",
              "format": "int32"
            }
          }
        ],
        "responses": {
          "200": {
            "description": "OK",
            "content": {
              "text/plain": {
                "schema": {
                  "$ref": "#/components/schemas/Cliente"
                }
              },
              "application/json": {
                "schema": {
                  "$ref": "#/components/schemas/Cliente"
                }
              },
              "text/json": {
                "schema": {
                  "$ref": "#/components/schemas/Cliente"
                }
              }
            }
          }
        }
      },
      "put": {
        "tags": [
          "Cliente"
        ],
        "parameters": [
          {
            "name": "id",
            "in": "path",
            "required": true,
            "schema": {
              "type": "integer",
              "format": "int32"
            }
          }
        ],
        "requestBody": {
          "content": {
            "application/json": {
              "schema": {
                "$ref": "#/components/schemas/Cliente"
              }
            },
            "text/json": {
              "schema": {
                "$ref": "#/components/schemas/Cliente"
              }
            },
            "application/*+json": {
              "schema": {
                "$ref": "#/components/schemas/Cliente"
              }
            }
          }
        },
        "responses": {
          "200": {
            "description": "OK"
          }
        }
      },
      "delete": {
        "tags": [
          "Cliente"
        ],
        "parameters": [
          {
            "name": "id",
            "in": "path",
            "required": true,
            "schema": {
              "type": "integer",
              "format": "int32"
            }
          }
        ],
        "responses": {
          "200": {
            "description": "OK"
          }
        }
      }
    },
    "/api/Contratos": {
      "post": {
        "tags": [
          "Contratos"
        ],
        "requestBody": {
          "content": {
            "application/json": {
              "schema": {
                "$ref": "#/components/schemas/Contrato"
              }
            },
            "text/json": {
              "schema": {
                "$ref": "#/components/schemas/Contrato"
              }
            },
            "application/*+json": {
              "schema": {
                "$ref": "#/components/schemas/Contrato"
              }
            }
          }
        },
        "responses": {
          "200": {
            "description": "OK",
            "content": {
              "text/plain": {
                "schema": {
                  "$ref": "#/components/schemas/Contrato"
                }
              },
              "application/json": {
                "schema": {
                  "$ref": "#/components/schemas/Contrato"
                }
              },
              "text/json": {
                "schema": {
                  "$ref": "#/components/schemas/Contrato"
                }
              }
            }
          }
        }
      }
    },
    "/api/Contratos/{id}": {
      "get": {
        "tags": [
          "Contratos"
        ],
        "parameters": [
          {
            "name": "id",
            "in": "path",
            "required": true,
            "schema": {
              "type": "integer",
              "format": "int32"
            }
          }
        ],
        "responses": {
          "200": {
            "description": "OK",
            "content": {
              "text/plain": {
                "schema": {
                  "$ref": "#/components/schemas/Contrato"
                }
              },
              "application/json": {
                "schema": {
                  "$ref": "#/components/schemas/Contrato"
                }
              },
              "text/json": {
                "schema": {
                  "$ref": "#/components/schemas/Contrato"
                }
              }
            }
          }
        }
      }
    },
    "/api/Contratos/{id}/encerrar": {
      "post": {
        "tags": [
          "Contratos"
        ],
        "parameters": [
          {
            "name": "id",
            "in": "path",
            "required": true,
            "schema": {
              "type": "integer",
              "format": "int32"
            }
          }
        ],
        "responses": {
          "200": {
            "description": "OK"
          }
        }
      }
    },
    "/": {
      "get": {
        "tags": [
          "Home"
        ],
        "responses": {
          "200": {
            "description": "OK"
          }
        }
      }
    },
    "/api/Imoveis": {
      "get": {
        "tags": [
          "Imoveis"
        ],
        "responses": {
          "200": {
            "description": "OK",
            "content": {
              "text/plain": {
                "schema": {
                  "type": "array",
                  "items": {
                    "$ref": "#/components/schemas/Imovel"
                  }
                }
              },
              "application/json": {
                "schema": {
                  "type": "array",
                  "items": {
                    "$ref": "#/components/schemas/Imovel"
                  }
                }
              },
              "text/json": {
                "schema": {
                  "type": "array",
                  "items": {
                    "$ref": "#/components/schemas/Imovel"
                  }
                }
              }
            }
          }
        }
      },
      "post": {
        "tags": [
          "Imoveis"
        ],
        "requestBody": {
          "content": {
            "application/json": {
              "schema": {
                "$ref": "#/components/schemas/Imovel"
              }
            },
            "text/json": {
              "schema": {
                "$ref": "#/components/schemas/Imovel"
              }
            },
            "application/*+json": {
              "schema": {
                "$ref": "#/components/schemas/Imovel"
              }
            }
          }
        },
        "responses": {
          "200": {
            "description": "OK",
            "content": {
              "text/plain": {
                "schema": {
                  "$ref": "#/components/schemas/Imovel"
                }
              },
              "application/json": {
                "schema": {
                  "$ref": "#/components/schemas/Imovel"
                }
              },
              "text/json": {
                "schema": {
                  "$ref": "#/components/schemas/Imovel"
                }
              }
            }
          }
        }
      }
    },
    "/api/Imoveis/{id}": {
      "put": {
        "tags": [
          "Imoveis"
        ],
        "parameters": [
          {
            "name": "id",
            "in": "path",
            "required": true,
            "schema": {
              "type": "integer",
              "format": "int32"
            }
          }
        ],
        "requestBody": {
          "content": {
            "application/json": {
              "schema": {
                "$ref": "#/components/schemas/Imovel"
              }
            },
            "text/json": {
              "schema": {
                "$ref": "#/components/schemas/Imovel"
              }
            },
            "application/*+json": {
              "schema": {
                "$ref": "#/components/schemas/Imovel"
              }
            }
          }
        },
        "responses": {
          "200": {
            "description": "OK"
          }
        }
      }
    },
    "/api/Login": {
      "post": {
        "tags": [
          "Login"
        ],
        "requestBody": {
          "content": {
            "application/json": {
              "schema": {
                "$ref": "#/components/schemas/LoginRequest"
              }
            },
            "text/json": {
              "schema": {
                "$ref": "#/components/schemas/LoginRequest"
              }
            },
            "application/*+json": {
              "schema": {
                "$ref": "#/components/schemas/LoginRequest"
              }
            }
          }
        },
        "responses": {
          "200": {
            "description": "OK"
          }
        }
      }
    },
    "/api/Login/seed": {
      "post": {
        "tags": [
          "Login"
        ],
        "responses": {
          "200": {
            "description": "OK"
          }
        }
      }
    },
    "/api/Produtos": {
      "get": {
        "tags": [
          "Produtos"
        ],
        "responses": {
          "200": {
            "description": "OK",
            "content": {
              "text/plain": {
                "schema": {
                  "type": "array",
                  "items": {
                    "$ref": "#/components/schemas/Produto"
                  }
                }
              },
              "application/json": {
                "schema": {
                  "type": "array",
                  "items": {
                    "$ref": "#/components/schemas/Produto"
                  }
                }
              },
              "text/json": {
                "schema": {
                  "type": "array",
                  "items": {
                    "$ref": "#/components/schemas/Produto"
                  }
                }
              }
            }
          }
        }
      },
      "post": {
        "tags": [
          "Produtos"
        ],
        "requestBody": {
          "content": {
            "application/json": {
              "schema": {
                "$ref": "#/components/schemas/Produto"
              }
            },
            "text/json": {
              "schema": {
                "$ref": "#/components/schemas/Produto"
              }
            },
            "application/*+json": {
              "schema": {
                "$ref": "#/components/schemas/Produto"
              }
            }
          }
        },
        "responses": {
          "200": {
            "description": "OK",
            "content": {
              "text/plain": {
                "schema": {
                  "$ref": "#/components/schemas/Produto"
                }
              },
              "application/json": {
                "schema": {
                  "$ref": "#/components/schemas/Produto"
                }
              },
              "text/json": {
                "schema": {
                  "$ref": "#/components/schemas/Produto"
                }
              }
            }
          }
        }
      }
    },
    "/api/Produtos/{id}": {
      "get": {
        "tags": [
          "Produtos"
        ],
        "parameters": [
          {
            "name": "id",
            "in": "path",
            "required": true,
            "schema": {
              "type": "integer",
              "format": "int32"
            }
          }
        ],
        "responses": {
          "200": {
            "description": "OK",
            "content": {
              "text/plain": {
                "schema": {
                  "$ref": "#/components/schemas/Produto"
                }
              },
              "application/json": {
                "schema": {
                  "$ref": "#/components/schemas/Produto"
                }
              },
              "text/json": {
                "schema": {
                  "$ref": "#/components/schemas/Produto"
                }
              }
            }
          }
        }
      },
      "put": {
        "tags": [
          "Produtos"
        ],
        "parameters": [
          {
            "name": "id",
            "in": "path",
            "required": true,
            "schema": {
              "type": "integer",
              "format": "int32"
            }
          }
        ],
        "requestBody": {
          "content": {
            "application/json": {
              "schema": {
                "$ref": "#/components/schemas/Produto"
              }
            },
            "text/json": {
              "schema": {
                "$ref": "#/components/schemas/Produto"
              }
            },
            "application/*+json": {
              "schema": {
                "$ref": "#/components/schemas/Produto"
              }
            }
          }
        },
        "responses": {
          "200": {
            "description": "OK"
          }
        }
      },
      "delete": {
        "tags": [
          "Produtos"
        ],
        "parameters": [
          {
            "name": "id",
            "in": "path",
            "required": true,
            "schema": {
              "type": "integer",
              "format": "int32"
            }
          }
        ],
        "responses": {
          "200": {
            "description": "OK"
          }
        }
      }
    }
  },
  "components": {
    "schemas": {
      "Cliente": {
        "required": [
          "nome"
        ],
        "type": "object",
        "properties": {
          "id": {
            "type": "integer",
            "format": "int32"
          },
          "nome": {
            "maxLength": 100,
            "minLength": 1,
            "type": "string"
          },
          "email": {
            "maxLength": 150,
            "type": "string",
            "nullable": true
          },
          "telefone": {
            "maxLength": 20,
            "type": "string",
            "nullable": true
          }
        },
        "additionalProperties": false
      },
      "Contrato": {
        "type": "object",
        "properties": {
          "id": {
            "type": "integer",
            "format": "int32"
          },
          "clienteId": {
            "type": "integer",
            "format": "int32"
          },
          "imovelId": {
            "type": "integer",
            "format": "int32"
          },
          "dataInicio": {
            "type": "string",
            "format": "date-time"
          },
          "dataFim": {
            "type": "string",
            "format": "date-time"
          },
          "ativo": {
            "type": "boolean"
          },
          "cliente": {
            "$ref": "#/components/schemas/Cliente"
          },
          "imovel": {
            "$ref": "#/components/schemas/Imovel"
          }
        },
        "additionalProperties": false
      },
      "Imovel": {
        "type": "object",
        "properties": {
          "id": {
            "type": "integer",
            "format": "int32"
          },
          "endereco": {
            "type": "string",
            "nullable": true
          },
          "tipo": {
            "type": "string",
            "nullable": true
          },
          "valor": {
            "type": "number",
            "format": "double"
          },
          "ativo": {
            "type": "boolean"
          }
        },
        "additionalProperties": false
      },
      "LoginRequest": {
        "type": "object",
        "properties": {
          "login": {
            "type": "string",
            "nullable": true
          },
          "senha": {
            "type": "string",
            "nullable": true
          }
        },
        "additionalProperties": false
      },
      "Produto": {
        "type": "object",
        "properties": {
          "id": {
            "type": "integer",
            "format": "int32"
          },
          "nome": {
            "type": "string",
            "nullable": true
          },
          "sku": {
            "type": "string",
            "nullable": true
          },
          "quantidade": {
            "type": "integer",
            "format": "int32"
          },
          "preco": {
            "type": "number",
            "format": "double"
          }
        },
        "additionalProperties": false
      }
    }
  }
}